pacemaker/__init__.py
pacemaker/_decorator.py
pacemaker/pacemaker.py
pacemaker-0.2.8.dist-info/LICENSE
pacemaker-0.2.8.dist-info/METADATA
pacemaker-0.2.8.dist-info/WHEEL
pacemaker-0.2.8.dist-info/top_level.txt
pacemaker-0.2.8.dist-info/RECORD
