Metadata-Version: 2.1
Name: pacemaker
Version: 0.2.8
Summary: To keep the old heart ticking
Home-page: https://github.com/mkeshav/pace-maker.git
Author: Keshav Murthy
Author-email: mkeshav@gmail.com
License: UNKNOWN
Platform: UNKNOWN
Classifier: Programming Language :: Python :: 3
Classifier: License :: OSI Approved :: MIT License
Classifier: Operating System :: OS Independent
